srcbpy/__init__.py
srcbpy/srcbpy.py
srcbpy-1.5.0.dist-info/LICENSE
srcbpy-1.5.0.dist-info/METADATA
srcbpy-1.5.0.dist-info/WHEEL
srcbpy-1.5.0.dist-info/top_level.txt
srcbpy-1.5.0.dist-info/RECORD
