Metadata-Version: 2.1
Name: srcbpy
Version: 1.5.0
Summary: A simple api wrapper for (pastebin) sourceb.in.
Home-page: https://github.com/jiroawesome/srcbpy
Author: JiroDeveloper
Author-email: contact@jiroawesome.tech
License: MIT License
Keywords: pastebin sourcebin sourceb.in
Classifier: Programming Language :: Python
Classifier: Programming Language :: Python :: 2
Classifier: Programming Language :: Python :: 2.7
Classifier: Programming Language :: Python :: 3
Classifier: Programming Language :: Python :: 3.5
Classifier: Programming Language :: Python :: 3.6
Classifier: Programming Language :: Python :: 3.7
Classifier: Programming Language :: Python :: 3.8
Classifier: Programming Language :: Python :: 3.9
Classifier: Programming Language :: Python :: 3.10
License-File: LICENSE
Requires-Dist: requests (==2.28.1)
